jfrog_curation_malicious_dummy_hash/__init__.py
jfrog_curation_malicious_dummy_hash-2.0.1.dist-info/METADATA
jfrog_curation_malicious_dummy_hash-2.0.1.dist-info/WHEEL
jfrog_curation_malicious_dummy_hash-2.0.1.dist-info/entry_points.txt
jfrog_curation_malicious_dummy_hash-2.0.1.dist-info/top_level.txt
jfrog_curation_malicious_dummy_hash-2.0.1.dist-info/RECORD
