Metadata-Version: 2.4
Name: jfrog-curation-malicious-dummy-hash
Version: 2.0.1
Summary: Jfrog Curation dummy malicious package
License: ISC
Requires-Python: >=3.7
